{
    "summary": "\n\nThe customer was having trouble with their phone and was told they were not eligible for an upgrade. After the agent looked at the customer's account, they found that the customer was in fact eligible for an upgrade. The agent then recommended the Contoso Lite model as a great option for the customer, given its lightweight and powerful features, latest operating system, and affordability.",
    "customerSentiment": "disappointed",
    "topic": "upgrade services",
    "product": "phone",
    "filename": "1_537_449_disappointed_upgrade services_phone_document.txt"
}