{
    "summary": "\n\nThe customer was assisted with downgrading their service plan with Contoso Wireless. The agent provided the customer with options for different service plans, as well as other products such as phones and accessories. The customer was also informed of any deals and discounts available, as well as the 30-day money back guarantee. The customer decided to go ahead with the downgrade.",
    "customerSentiment": "confused",
    "topic": "downgrade services",
    "product": "other",
    "filename": "349_611_523_confused_downgrade services_other_document.txt"
}