{
    "summary": "\n\nThe customer had an unsatisfactory experience with Contoso Wireless' upgrade services and the agent provided them with information about the various products, plans, and services offered by the company. The agent also gave details about the features of their phones, including the camera, battery life, and accessories. Lastly, they discussed the warranty coverage provided by Contoso Wireless and how long it lasts.",
    "customerSentiment": "upset",
    "topic": "upgrade services",
    "product": "other",
    "filename": "378_641_553_upset_upgrade services_other_document.txt"
}