{
    "summary": "\n\nThe customer reached out to Contoso Wireless with an issue regarding their upgrade services. The customer purchased a new phone that was not functioning properly and had not received help after two weeks. The agent provided assistance by asking for more information about the product and then provided the customer with the serial number of the device. The agent then offered to provide the customer with a list of available products that would be a better fit for their needs.",
    "customerSentiment": "negative",
    "topic": "upgrade services",
    "product": "other",
    "filename": "626_582_494_negative_upgrade services_other_document.txt"
}